ecommerce_extensions/__init__.py
ecommerce_extensions/apps.py
ecommerce_extensions/urls.py
ecommerce_extensions/auth_backends/__init__.py
ecommerce_extensions/auth_backends/backends.py
ecommerce_extensions/core/__init__.py
ecommerce_extensions/core/mixins.py
ecommerce_extensions/core/permissions.py
ecommerce_extensions/core/utils.py
ecommerce_extensions/payment/__init__.py
ecommerce_extensions/payment/constants.py
ecommerce_extensions/payment/encryption_utils.py
ecommerce_extensions/payment/exceptions.py
ecommerce_extensions/payment/urls.py
ecommerce_extensions/payment/processors/__init__.py
ecommerce_extensions/payment/processors/edupay.py
ecommerce_extensions/payment/processors/fomopay.py
ecommerce_extensions/payment/processors/payu.py
ecommerce_extensions/payment/tests/__init__.py
ecommerce_extensions/payment/tests/exceptions.py
ecommerce_extensions/payment/tests/processors/__init__.py
ecommerce_extensions/payment/tests/views/__init__.py
ecommerce_extensions/payment/tests/views/tests_edupay.py
ecommerce_extensions/payment/tests/views/tests_fomopay.py
ecommerce_extensions/payment/tests/views/tests_payu.py
ecommerce_extensions/payment/views/__init__.py
ecommerce_extensions/payment/views/edupay.py
ecommerce_extensions/payment/views/fomopay.py
ecommerce_extensions/payment/views/payu.py
ecommerce_extensions/settings/__init__.py
ecommerce_extensions/settings/common.py
ecommerce_extensions/settings/production.py
ecommerce_extensions/settings/test.py
ecommerce_extensions/static/images/WeChat_APP_Icon.png
ecommerce_extensions/static/js/payment_processors/fomopay.js
ecommerce_extensions/templates/payment/fomopay.html
ecommerce_extensions/templates/payment/pending_status.html
ecommerce_extensions/tenant/__init__.py
ecommerce_extensions/tenant/admin.py
ecommerce_extensions/tenant/apps.py
ecommerce_extensions/tenant/conf.py
ecommerce_extensions/tenant/context_processors.py
ecommerce_extensions/tenant/extra_html.py
ecommerce_extensions/tenant/extra_options.py
ecommerce_extensions-1.4.1.dist-info/AUTHORS.txt
ecommerce_extensions-1.4.1.dist-info/LICENSE.txt
ecommerce_extensions-1.4.1.dist-info/METADATA
ecommerce_extensions-1.4.1.dist-info/WHEEL
ecommerce_extensions-1.4.1.dist-info/top_level.txt
ecommerce_extensions-1.4.1.dist-info/RECORD
