Metadata-Version: 2.1
Name: ecommerce-extensions
Version: 1.4.1
Summary: Django eduNEXT ecommerce-extensions app.
Home-page: UNKNOWN
Author: eduNEXT
Author-email: contact@edunext.co
License: AGPL
Platform: UNKNOWN
Classifier: Development Status :: 5 - Production/Stable
Classifier: Framework :: Django :: 1.11
Classifier: Framework :: Django :: 2.2
Classifier: Intended Audience :: Developers
Classifier: License :: OSI Approved :: GNU Affero General Public License v3
Classifier: Operating System :: OS Independent
Classifier: Programming Language :: Python :: 2
Classifier: Programming Language :: Python :: 2.7
Classifier: Programming Language :: Python :: 3
Classifier: Programming Language :: Python :: 3.5
Classifier: Programming Language :: Python :: 3.8
Requires-Dist: django-crum
Requires-Dist: django-compressor
Requires-Dist: qrcode
Requires-Dist: sorl-thumbnail
Requires-Dist: edx-auth-backends
Requires-Dist: Django
Requires-Dist: cryptography
Requires-Dist: django-oscar
Requires-Dist: jsonfield2
Requires-Dist: djangorestframework
Provides-Extra: sentry
Requires-Dist: sentry-sdk (==1.5.1) ; extra == 'sentry'
